setup.cfg
setup.py
axosoft_api/__init__.py
axosoft_api/config.py
axosoft_api/validate.py
axosoft_api.egg-info/PKG-INFO
axosoft_api.egg-info/SOURCES.txt
axosoft_api.egg-info/dependency_links.txt
axosoft_api.egg-info/requires.txt
axosoft_api.egg-info/top_level.txt