Metadata-Version: 1.1
Name: axosoft-api
Version: 0.1.0
Summary: An Axosoft API Client
Home-page: http://github.com/ckaznocha/axosoft-python
Author: Clifton Kaznocha
Author-email: clifton@kaznocha.com
License: MIT
Download-URL: http://github.com/ckaznocha/axosoft-python/tarball/0.1
Keywords: Axosoft,scrum,api,ontime
Platform: UNKNOWN
